intra_prediction.srcs/sources_1/new/planar_prediction.sv
`timescale 1ns / 1ps
//////////////////////////////////////////////////////////////////////////////////
// Company: 
// Engineer: 
// 
// Create Date: 08/11/2025 12:03:44 AM
// Design Name: 
// Module Name: planar_prediction
// Project Name: 
// Target Devices: 
// Tool Versions: 
// Description: 
// 
// Dependencies: 
// 
// Revision:
// Revision 0.01 - File Created
// Additional Comments:
// 
//////////////////////////////////////////////////////////////////////////////////


module planar_prediction(
    input clk,
    input rst,
    input [7:0] data_in,
    input [4:0]x,
    input [4:0]y,
    output logic [7:0] Predict_planar
    );
    
  parameter N=32;  
    
    
 //Horizontal and Vertical Arrays
 logic [7:0] hor[0:31][0:31]; //32 x32 horizontal Array   
 logic [7:0] ver[0:31][0:31]; //32 x32 vertical Array   
     
 //Sample Reference Sample Array 2 D
 logic [7:0] p[0:31][0:31];     

// 2D array to store planar prediction results
logic [7:0] predict_sum[0:31][0:31];

integer i;
integer j;

always_ff@(posedge clk)
if(rst)
for (i=0; i<31; i = i+1)begin     
    for (j=0; j<31; j = j+1)begin
    p[i][j]<=0;
    end
end
else    
    p[x][y]<=data_in;
    

//assign Predict_planar=p[x][y];

// Planar prediction computation
    logic [15:0] sum;
    always_comb begin
        // Planar formula from H.265 spec using p[] as reference storage
        sum =  ( ( (N-1 - x) * p[0][y+1] ) +    // left ref     hor[x][y] 
               ( (x+1)     * p[N-1][y+1] ) +  // right ref
               ( (N-1 - y) * p[x+1][0] ) +    // top ref      ver[x][y]
               ( (y+1)     * p[x+1][N-1] ) +  // bottom ref
               N)  ;                             

        Predict_planar = sum / (2 * N);
    end

    // Store prediction results in predict_sum array
    always_ff @(posedge clk) begin
        if (!rst) begin
            predict_sum[x][y] <= Predict_planar;
        end
    end
    
    
endmodule

intra_prediction.srcs/sim_1/new/tb_planar_prediction.sv
`timescale 1ns / 1ps
//////////////////////////////////////////////////////////////////////////////////
// Company: 
// Engineer: 
// 
// Create Date: 08/20/2025 09:54:18 PM
// Design Name: 
// Module Name: tb_planar_prediction
// Project Name: 
// Target Devices: 
// Tool Versions: 
// Description: 
// 
// Dependencies: 
// 
// Revision:
// Revision 0.01 - File Created
// Additional Comments:
// 
//////////////////////////////////////////////////////////////////////////////////


`timescale 1ns/1ps

module tb_planar_prediction;

  // Clock and reset
  logic clk;
  logic rst;

  // DUT signals
  logic [7:0] data_in;
  logic [4:0] x, y;
  logic [7:0] Predict_planar;

  // Instantiate DUT
  planar_prediction dut (
    .clk(clk),
    .rst(rst),
    .data_in(data_in),
    .x(x),
    .y(y),
    .Predict_planar(Predict_planar)
  );

  // Clock generation (10ns period)
  initial clk = 1'b0;
  always #5 clk = ~clk;

  // VCD for waveform viewing
  initial begin
    $dumpfile("planar_prediction_tb.vcd");
    $dumpvars(0, tb_planar_prediction);
  end

   integer i;
   integer j;


  // Test stimulus
  initial begin
    // Initialize signals
    rst     = 1;
    data_in = 0;
    x       = 0;
    y       = 0;

    // Hold reset for a few cycles
    repeat (3) @(posedge clk);
    rst = 0;

    // Fill Our Sample Array First 
    for ( i=0; i< 10 ; i=i+1) begin
     for (j=0; j<10; j=j +1) begin
     #5 data_in=$random;
     #1 x=i;
     #1 y=j;
     end
    
    end
    
    #100
    // ---------------------------------------------------
    // Finish simulation
    // ---------------------------------------------------
    $display("\nSimulation complete at %0t", $time);
    $finish;
  end

endmodule

intra_prediction.sim/sim_1/behav/xsim/planar_prediction_tb.vcd
$date
   Wed Aug 20 23:47:29 2025
$end
$version
  2018.2
$end
$timescale
  1ps
$end
$scope module tb_planar_prediction $end
$var reg 1 ! clk $end
$var reg 1 " rst $end
$var reg 8 # data_in [7:0] $end
$var reg 5 $ x [4:0] $end
$var reg 5 % y [4:0] $end
$var reg 8 & Predict_planar [7:0] $end
$var integer 32 ' i $end
$var integer 32 ( j $end
$scope module dut $end
$var wire 1 ) clk $end
$var wire 1 * rst $end
$var wire 8 + data_in [7:0] $end
$var wire 5 , x [4:0] $end
$var wire 5 - y [4:0] $end
$var reg 8 & Predict_planar [7:0] $end
$var integer 32 . i $end
$var integer 32 / j $end
$var reg 16 0 sum [15:0] $end
$var parameter 32 1 N [31:0] $end
$upscope $end
$upscope $end
$enddefinitions $end
#0
$dumpvars
0!
1"
b0 #
b0 $
b0 %
bx &
bx '
bx (
0)
1*
b0 +
b0 ,
b0 -
bx .
bx /
bx 0
b100000 1
$end
#5000
1!
b0 &
1)
b100000 .
b100000 /
b0 0
#10000
0!
0)
#15000
1!
1)
b100000 .
b100000 /
#20000
0!
0)
#25000
1!
0"
b0 '
b0 (
1)
0*
b100000 0
#30000
0!
b100100 #
0)
b100100 +
#31000
b0 $
#32000
b0 %
b1 (
#35000
1!
1)
#37000
b10000001 #
b10000001 +
#38000
b0 $
#39000
b1 %
b10 (
b1 -
#40000
0!
0)
#44000
b1001 #
b1001 +
#45000
1!
b0 $
1)
#46000
b10 %
b11 (
b10 -
#50000
0!
0)
#51000
b1100011 #
b1100011 +
#52000
b0 $
#53000
b11 %
b100 (
b11 -
#55000
1!
1)
#58000
b1101 #
b1101 +
#59000
b0 $
#60000
0!
b100 %
b101 (
0)
b100 -
#65000
1!
b10001101 #
1)
b10001101 +
#66000
b0 $
#67000
b101 %
b110 (
b101 -
#70000
0!
0)
#72000
b1100101 #
b1100101 +
#73000
b0 $
#74000
b110 %
b111 (
b110 -
#75000
1!
1)
#79000
b10010 #
b10010 +
#80000
0!
b0 $
0)
#81000
b111 %
b1000 (
b111 -
#85000
1!
1)
#86000
b1 #
b1 +
#87000
b0 $
#88000
b1000 %
b1001 (
b1000 -
#90000
0!
0)
#93000
b1101 #
b1101 +
#94000
b0 $
#95000
1!
b1001 %
b1 '
b0 (
1)
b1001 -
#100000
0!
b1110110 #
0)
b1110110 +
#101000
b1 $
b1 ,
#102000
b0 %
b1 (
b0 -
#105000
1!
1)
b100101110 0
#107000
b111101 #
b111101 +
#108000
b1 $
#109000
b1 %
b10 (
b1 -
#110000
0!
0)
#114000
b11101101 #
b11101101 +
#115000
1!
b1 $
b100 &
1)
b100000 0
#116000
b10 %
b11 (
b10 -
#120000
0!
0)
#121000
b10001100 #
b10001100 +
#122000
b1 $
#123000
b11 %
b100 (
b11 -
#125000
1!
b0 &
1)
b1000010100110 0
#128000
b11111001 #
b11111001 +
#129000
b1 $
#130000
0!
b100 %
b101 (
0)
b100 -
#135000
1!
b11000110 #
b1000010 &
1)
b11000110 +
b100000 0
#136000
b1 $
#137000
b101 %
b110 (
b101 -
#140000
0!
0)
#142000
b11000101 #
b11000101 +
#143000
b1 $
#144000
b110 %
b111 (
b110 -
#145000
1!
b0 &
1)
b1000111100 0
#149000
b10101010 #
b10101010 +
#150000
0!
b1 $
0)
#151000
b111 %
b1000 (
b111 -
#155000
1!
b1000 &
1)
b100000 0
#156000
b11100101 #
b11100101 +
#157000
b1 $
#158000
b1000 %
b1001 (
b1000 -
#160000
0!
0)
#163000
b1110111 #
b1110111 +
#164000
b1 $
#165000
1!
b1001 %
b0 &
b10 '
b0 (
1)
b1001 -
#170000
0!
b10010 #
0)
b10010 +
#171000
b10 $
b10 ,
#172000
b0 %
b1 (
b0 -
#175000
1!
1)
b100100101 0
#177000
b10001111 #
b10001111 +
#178000
b10 $
#179000
b1 %
b10 (
b1 -
#180000
0!
0)
#184000
b11110010 #
b11110010 +
#185000
1!
b10 $
b100 &
1)
b100000 0
#186000
b10 %
b11 (
b10 -
#190000
0!
0)
#191000
b11001110 #
b11001110 +
#192000
b10 $
#193000
b11 %
b100 (
b11 -
#195000
1!
b0 &
1)
b1000000011001 0
#198000
b11101000 #
b11101000 +
#199000
b10 $
#200000
0!
b100 %
b101 (
0)
b100 -
#205000
1!
b11000101 #
b1000000 &
1)
b11000101 +
b100000 0
#206000
b10 $
#207000
b101 %
b110 (
b101 -
#210000
0!
0)
#212000
b1011100 #
b1011100 +
#213000
b10 $
#214000
b110 %
b111 (
b110 -
#215000
1!
b0 &
1)
b1000101010 0
#219000
b10111101 #
b10111101 +
#220000
0!
b10 $
0)
#221000
b111 %
b1000 (
b111 -
#225000
1!
b1000 &
1)
b100000 0
#226000
b101101 #
b101101 +
#227000
b10 $
#228000
b1000 %
b1001 (
b1000 -
#230000
0!
0)
#233000
b1100101 #
b1100101 +
#234000
b10 $
#235000
1!
b1001 %
b0 &
b11 '
b0 (
1)
b1001 -
#240000
0!
b1100011 #
0)
b1100011 +
#241000
b11 $
b11 ,
#242000
b0 %
b1 (
b0 -
#245000
1!
1)
b100011100 0
#247000
b1010 #
b1010 +
#248000
b11 $
#249000
b1 %
b10 (
b1 -
#250000
0!
0)
#254000
b10000000 #
b10000000 +
#255000
1!
b11 $
b100 &
1)
b100000 0
#256000
b10 %
b11 (
b10 -
#260000
0!
0)
#261000
b100000 #
b100000 +
#262000
b11 $
#263000
b11 %
b100 (
b11 -
#265000
1!
b0 &
1)
b111110001100 0
#268000
b10101010 #
b10101010 +
#269000
b11 $
#270000
0!
b100 %
b101 (
0)
b100 -
#275000
1!
b10011101 #
b111110 &
1)
b10011101 +
b100000 0
#276000
b11 $
#277000
b101 %
b110 (
b101 -
#280000
0!
0)
#282000
b10010110 #
b10010110 +
#283000
b11 $
#284000
b110 %
b111 (
b110 -
#285000
1!
b0 &
1)
b1000011000 0
#289000
b10011 #
b10011 +
#290000
0!
b11 $
0)
#291000
b111 %
b1000 (
b111 -
#295000
1!
b1000 &
1)
b100000 0
#296000
b1101 #
b1101 +
#297000
b11 $
#298000
b1000 %
b1001 (
b1000 -
#300000
0!
0)
#303000
b1010011 #
b1010011 +
#304000
b11 $
#305000
1!
b1001 %
b0 &
b100 '
b0 (
1)
b1001 -
#310000
0!
b1101011 #
0)
b1101011 +
#311000
b100 $
b100 ,
#312000
b0 %
b1 (
b0 -
#315000
1!
1)
b100010011 0
#317000
b11010101 #
b11010101 +
#318000
b100 $
#319000
b1 %
b10 (
b1 -
#320000
0!
0)
#324000
b10 #
b10 +
#325000
1!
b100 $
b100 &
1)
b100000 0
#326000
b10 %
b11 (
b10 -
#330000
0!
0)
#331000
b10101110 #
b10101110 +
#332000
b100 $
#333000
b11 %
b100 (
b11 -
#335000
1!
b0 &
1)
b111011111111 0
#338000
b11101 #
b11101 +
#339000
b100 $
#340000
0!
b100 %
b101 (
0)
b100 -
#345000
1!
b11001111 #
b111011 &
1)
b11001111 +
b100000 0
#346000
b100 $
#347000
b101 %
b110 (
b101 -
#350000
0!
0)
#352000
b100011 #
b100011 +
#353000
b100 $
#354000
b110 %
b111 (
b110 -
#355000
1!
b0 &
1)
b1000000110 0
#359000
b1010 #
b1010 +
#360000
0!
b100 $
0)
#361000
b111 %
b1000 (
b111 -
#365000
1!
b1000 &
1)
b100000 0
#366000
b11001010 #
b11001010 +
#367000
b100 $
#368000
b1000 %
b1001 (
b1000 -
#370000
0!
0)
#373000
b111100 #
b111100 +
#374000
b100 $
#375000
1!
b1001 %
b0 &
b101 '
b0 (
1)
b1001 -
#380000
0!
b11110010 #
0)
b11110010 +
#381000
b101 $
b101 ,
#382000
b0 %
b1 (
b0 -
#385000
1!
1)
b100001010 0
#387000
b10001010 #
b10001010 +
#388000
b101 $
#389000
b1 %
b10 (
b1 -
#390000
0!
0)
#394000
b1000001 #
b1000001 +
#395000
1!
b101 $
b100 &
1)
b100000 0
#396000
b10 %
b11 (
b10 -
#400000
0!
0)
#401000
b11011000 #
b11011000 +
#402000
b101 $
#403000
b11 %
b100 (
b11 -
#405000
1!
b0 &
1)
b111001110010 0
#408000
b1111000 #
b1111000 +
#409000
b101 $
#410000
0!
b100 %
b101 (
0)
b100 -
#415000
1!
b10001001 #
b111001 &
1)
b10001001 +
b100000 0
#416000
b101 $
#417000
b101 %
b110 (
b101 -
#420000
0!
0)
#422000
b11101011 #
b11101011 +
#423000
b101 $
#424000
b110 %
b111 (
b110 -
#425000
1!
b0 &
1)
b111110100 0
#429000
b10110110 #
b10110110 +
#430000
0!
b101 $
0)
#431000
b111 %
b1000 (
b111 -
#435000
1!
b111 &
1)
b100000 0
#436000
b11000110 #
b11000110 +
#437000
b101 $
#438000
b1000 %
b1001 (
b1000 -
#440000
0!
0)
#443000
b10101110 #
b10101110 +
#444000
b101 $
#445000
1!
b1001 %
b0 &
b110 '
b0 (
1)
b1001 -
#450000
0!
b10111100 #
0)
b10111100 +
#451000
b110 $
b110 ,
#452000
b0 %
b1 (
b0 -
#455000
1!
1)
b100000001 0
#457000
b101010 #
b101010 +
#458000
b110 $
#459000
b1 %
b10 (
b1 -
#460000
0!
0)
#464000
b1011 #
b1011 +
#465000
1!
b110 $
b100 &
1)
b100000 0
#466000
b10 %
b11 (
b10 -
#470000
0!
0)
#471000
b1110001 #
b1110001 +
#472000
b110 $
#473000
b11 %
b100 (
b11 -
#475000
1!
b0 &
1)
b110111100101 0
#478000
b10000101 #
b10000101 +
#479000
b110 $
#480000
0!
b100 %
b101 (
0)
b100 -
#485000
1!
b1001111 #
b110111 &
1)
b1001111 +
b100000 0
#486000
b110 $
#487000
b101 %
b110 (
b101 -
#490000
0!
0)
#492000
b111011 #
b111011 +
#493000
b110 $
#494000
b110 %
b111 (
b110 -
#495000
1!
b0 &
1)
b111100010 0
#499000
b111010 #
b111010 +
#500000
0!
b110 $
0)
#501000
b111 %
b1000 (
b111 -
#505000
1!
b111 &
1)
b100000 0
#506000
b1111110 #
b1111110 +
#507000
b110 $
#508000
b1000 %
b1001 (
b1000 -
#510000
0!
0)
#513000
b10101 #
b10101 +
#514000
b110 $
#515000
1!
b1001 %
b0 &
b111 '
b0 (
1)
b1001 -
#520000
0!
b11110001 #
0)
b11110001 +
#521000
b111 $
b111 ,
#522000
b0 %
b1 (
b0 -
#525000
1!
1)
b11111000 0
#527000
b11011001 #
b11011001 +
#528000
b111 $
#529000
b1 %
b10 (
b1 -
#530000
0!
0)
#534000
b1100010 #
b1100010 +
#535000
1!
b111 $
b11 &
1)
b100000 0
#536000
b10 %
b11 (
b10 -
#540000
0!
0)
#541000
b1001100 #
b1001100 +
#542000
b111 $
#543000
b11 %
b100 (
b11 -
#545000
1!
b0 &
1)
b110101011000 0
#548000
b10011111 #
b10011111 +
#549000
b111 $
#550000
0!
b100 %
b101 (
0)
b100 -
#555000
1!
b10001111 #
b110101 &
1)
b10001111 +
b100000 0
#556000
b111 $
#557000
b101 %
b110 (
b101 -
#560000
0!
0)
#562000
b11111000 #
b11111000 +
#563000
b111 $
#564000
b110 %
b111 (
b110 -
#565000
1!
b0 &
1)
b111010000 0
#569000
b10110111 #
b10110111 +
#570000
0!
b111 $
0)
#571000
b111 %
b1000 (
b111 -
#575000
1!
b111 &
1)
b100000 0
#576000
b10011111 #
b10011111 +
#577000
b111 $
#578000
b1000 %
b1001 (
b1000 -
#580000
0!
0)
#583000
b1011100 #
b1011100 +
#584000
b111 $
#585000
1!
b1001 %
b0 &
b1000 '
b0 (
1)
b1001 -
#590000
0!
b1011011 #
0)
b1011011 +
#591000
b1000 $
b1000 ,
#592000
b0 %
b1 (
b0 -
#595000
1!
1)
b11101111 0
#597000
b10001001 #
b10001001 +
#598000
b1000 $
#599000
b1 %
b10 (
b1 -
#600000
0!
0)
#604000
b1001001 #
b1001001 +
#605000
1!
b1000 $
b11 &
1)
b100000 0
#606000
b10 %
b11 (
b10 -
#610000
0!
0)
#611000
b11010000 #
b11010000 +
#612000
b1000 $
#613000
b11 %
b100 (
b11 -
#615000
1!
b0 &
1)
b110011001011 0
#618000
b11010111 #
b11010111 +
#619000
b1000 $
#620000
0!
b100 %
b101 (
0)
b100 -
#625000
1!
b1010001 #
b110011 &
1)
b1010001 +
b100000 0
#626000
b1000 $
#627000
b101 %
b110 (
b101 -
#630000
0!
0)
#632000
b10010110 #
b10010110 +
#633000
b1000 $
#634000
b110 %
b111 (
b110 -
#635000
1!
b0 &
1)
b110111110 0
#639000
b1100 #
b1100 +
#640000
0!
b1000 $
0)
#641000
b111 %
b1000 (
b111 -
#645000
1!
b110 &
1)
b100000 0
#646000
b11000010 #
b11000010 +
#647000
b1000 $
#648000
b1000 %
b1001 (
b1000 -
#650000
0!
0)
#653000
b11001000 #
b11001000 +
#654000
b1000 $
#655000
1!
b1001 %
b0 &
b1001 '
b0 (
1)
b1001 -
#660000
0!
b1110111 #
0)
b1110111 +
#661000
b1001 $
b1001 ,
#662000
b0 %
b1 (
b0 -
#665000
1!
1)
b11100110 0
#667000
b111101 #
b111101 +
#668000
b1001 $
#669000
b1 %
b10 (
b1 -
#670000
0!
0)
#674000
b10010 #
b10010 +
#675000
1!
b1001 $
b11 &
1)
b100000 0
#676000
b10 %
b11 (
b10 -
#680000
0!
0)
#681000
b1111110 #
b1111110 +
#682000
b1001 $
#683000
b11 %
b100 (
b11 -
#685000
1!
b0 &
1)
b110000111110 0
#688000
b1101101 #
b1101101 +
#689000
b1001 $
#690000
0!
b100 %
b101 (
0)
b100 -
#695000
1!
b111001 #
b110000 &
1)
b111001 +
b100000 0
#696000
b1001 $
#697000
b101 %
b110 (
b101 -
#700000
0!
0)
#702000
b11111 #
b11111 +
#703000
b1001 $
#704000
b110 %
b111 (
b110 -
#705000
1!
b0 &
1)
b110101100 0
#709000
b11010011 #
b11010011 +
#710000
0!
b1001 $
0)
#711000
b111 %
b1000 (
b111 -
#715000
1!
b110 &
1)
b100000 0
#716000
b10000101 #
b10000101 +
#717000
b1001 $
#718000
b1000 %
b1001 (
b1000 -
#720000
0!
0)
#723000
b1111000 #
b1111000 +
#724000
b1001 $
#725000
1!
b1001 %
b0 &
b1010 '
b1010 (
1)
b1001 -
