intra_prediction.srcs/sources_1/new/reference_sample_arrays.sv
`timescale 1ns / 1ps
//////////////////////////////////////////////////////////////////////////////////
// Company: 
// Engineer: 
// 
// Create Date: 08/20/2025 02:21:47 AM
// Design Name: 
// Module Name: reference_sample_arrays
// Project Name: 
// Target Devices: 
// Tool Versions: 
// Description: 
// 
// Dependencies: 
// 
// Revision:
// Revision 0.01 - File Created
// Additional Comments:
// 
//////////////////////////////////////////////////////////////////////////////////


module reference_sample_arrays(
    input clk,
    input rst,
    input logic signed [3:0]x,
    input logic signed [3:0]y,
    input logic signed [7:0]B,
    output logic [7:0] ref_out1,   //For X
    output logic [7:0] ref_out2   //For Y
     );
    
    logic [7:0] p [0:7][0:7]; //2 D Pixel Array
    
    logic [7:0] ref_x[0:7];  //Reference Array X
    logic [7:0] ref_y[0:7]; //Reference Array y
        
        
    // The values of p are determined by other inputs or logic
        always_comb begin
            for (int i = 0; i < 8; i++) begin
                for (int j = 0; j < 8; j++) begin
                    // Example: Initialize based on inputs x and y
                    p[i][j] = (i * 8) + j; 
                end
            end
        end    
    
    //Reference X Equations
    always_comb begin
    if(x>0)
    ref_x[x]= p[x][0]; //Equation 4.8  x > 0 Vertical Mode  
    else 
    ref_x[x]=(p[0][-1 + (x*B) + 128 >>8]) ; // Equation 4.10 
    end
    
    //Reference Y Equations
        always_comb begin
        if(y>0)
        ref_y[y]= p[0][y]; //Equation 4.9  x > 0 Horizontal Mode p[-1][-1+y]  
        else 
        ref_y[y]= p[-1 + (y*B) + 128 >> 8][0] ; // Equation 4.11 
        end
        
    always_ff@(posedge clk)
    if(rst)
    ref_out1<=0;
    else
    ref_out1<=ref_x[x];
    
    always_ff@(posedge clk)
     if(rst)
     ref_out2<=0;
     else
    ref_out2<=ref_y[y];
        
    
endmodule

intra_prediction.srcs/sim_1/new/tb_reference_array.sv
`timescale 1ns / 1ps
//////////////////////////////////////////////////////////////////////////////////
// Company: 
// Engineer: 
// 
// Create Date: 08/20/2025 02:42:13 AM
// Design Name: 
// Module Name: tb_reference_array
// Project Name: 
// Target Devices: 
// Tool Versions: 
// Description: 
// 
// Dependencies: 
// 
// Revision:
// Revision 0.01 - File Created
// Additional Comments:
// 
//////////////////////////////////////////////////////////////////////////////////

`timescale 1ns/1ps

module tb_reference_sample_arrays;

  // Testbench signals
  logic clk;
  logic rst;
  logic [3:0] x, y;
  logic [7:0] B;
  logic [7:0] ref_out1, ref_out2;

  // Instantiate DUT
  reference_sample_arrays dut (
    .clk(clk),
    .rst(rst),
    .x(x),
    .y(y),
    .B(B),
    .ref_out1(ref_out1),
    .ref_out2(ref_out2)
  );

  // Clock generation
  initial clk = 0;
  always #5 clk = ~clk;   // 10ns period

  // Stimulus
  initial begin
    // Initialize
    rst = 1;
    B = 8'd5;   // Example value for B
    x = 0;
    y = 0;

    // Apply reset
    #20;
    rst = 0;


        for (int xi = 0; xi <= 15; xi++) begin
      for (int yi = 0; yi <= 15; yi++) begin
        @(posedge clk);  // <<< Apply at clock edge
        x <= xi;
        y <= yi;
        B <= 8'd5; // Example constant
        @(posedge clk); // Wait for DUT to update outputs
    
        $display("Time=%0t | x=%0d | y=%0d | ref_out1=%0d | ref_out2=%0d",
                 $time, x, y, ref_out1, ref_out2);
      end
    end


    // End simulation
    $display("Simulation completed at %0t", $time);
    $finish;
  end

  // VCD dump for GTKWave
  initial begin
    $dumpfile("reference_sample_arrays_tb.vcd");
    $dumpvars(0, tb_reference_sample_arrays);
  end

endmodule

intra_prediction.sim/sim_1/behav/xsim/reference_sample_arrays_tb.vcd
$date
   Wed Aug 20 21:40:39 2025
$end
$version
  2018.2
$end
$timescale
  1ps
$end
$scope module tb_reference_sample_arrays $end
$var reg 1 ! clk $end
$var reg 1 " rst $end
$var reg 4 # x [3:0] $end
$var reg 4 $ y [3:0] $end
$var reg 8 % B [7:0] $end
$var reg 8 & ref_out1 [7:0] $end
$var reg 8 ' ref_out2 [7:0] $end
$scope module dut $end
$var wire 1 ( clk $end
$var wire 1 ) rst $end
$var wire 4 * x [3:0] $end
$var wire 4 + y [3:0] $end
$var wire 8 , B [7:0] $end
$var reg 8 & ref_out1 [7:0] $end
$var reg 8 ' ref_out2 [7:0] $end
$scope begin Block41_1 $end
$var reg 32 - i $end
$scope begin Block42_2 $end
$var reg 32 . j $end
$upscope $end
$upscope $end
$upscope $end
$scope begin Block61_10 $end
$var reg 32 / xi $end
$scope begin Block62_11 $end
$var reg 32 0 yi $end
$upscope $end
$upscope $end
$upscope $end
$enddefinitions $end
#0
$dumpvars
0!
1"
b0 #
b0 $
b101 %
bx &
bx '
0(
1)
b0 *
b0 +
b101 ,
b1000 -
b1000 .
b0 /
b0 0
$end
#5000
1!
b0 &
b0 '
1(
#10000
0!
0(
#15000
1!
1(
#20000
0!
0"
0(
0)
#25000
1!
b0 #
b0 $
b101 %
1(
#30000
0!
0(
#35000
1!
1(
b1 0
#40000
0!
0(
#45000
1!
b0 #
b1 $
b101 %
1(
b1 +
#50000
0!
0(
#55000
1!
b1 '
1(
b10 0
#60000
0!
0(
#65000
1!
b0 #
b10 $
b101 %
1(
b10 +
#70000
0!
0(
#75000
1!
b10 '
1(
b11 0
#80000
0!
0(
#85000
1!
b0 #
b11 $
b101 %
1(
b11 +
#90000
0!
0(
#95000
1!
b11 '
1(
b100 0
#100000
0!
0(
#105000
1!
b0 #
b100 $
b101 %
1(
b100 +
#110000
0!
0(
#115000
1!
b100 '
1(
b101 0
#120000
0!
0(
#125000
1!
b0 #
b101 $
b101 %
1(
b101 +
#130000
0!
0(
#135000
1!
b101 '
1(
b110 0
#140000
0!
0(
#145000
1!
b0 #
b110 $
b101 %
1(
b110 +
#150000
0!
0(
#155000
1!
b110 '
1(
b111 0
#160000
0!
0(
#165000
1!
b0 #
b111 $
b101 %
1(
b111 +
#170000
0!
0(
#175000
1!
b111 '
1(
b1000 0
#180000
0!
0(
#185000
1!
b0 #
b1000 $
b101 %
1(
b1000 +
#190000
0!
0(
#195000
1!
bx '
1(
b1001 0
#200000
0!
0(
#205000
1!
b0 #
b1001 $
b101 %
1(
b1001 +
#210000
0!
0(
#215000
1!
1(
b1010 0
#220000
0!
0(
#225000
1!
b0 #
b1010 $
b101 %
1(
b1010 +
#230000
0!
0(
#235000
1!
1(
b1011 0
#240000
0!
0(
#245000
1!
b0 #
b1011 $
b101 %
1(
b1011 +
#250000
0!
0(
#255000
1!
1(
b1100 0
#260000
0!
0(
#265000
1!
b0 #
b1100 $
b101 %
1(
b1100 +
#270000
0!
0(
#275000
1!
1(
b1101 0
#280000
0!
0(
#285000
1!
b0 #
b1101 $
b101 %
1(
b1101 +
#290000
0!
0(
#295000
1!
1(
b1110 0
#300000
0!
0(
#305000
1!
b0 #
b1110 $
b101 %
1(
b1110 +
#310000
0!
0(
#315000
1!
1(
b1111 0
#320000
0!
0(
#325000
1!
b0 #
b1111 $
b101 %
1(
b1111 +
#330000
0!
0(
#335000
1!
1(
b1 /
b0 0
#340000
0!
0(
#345000
1!
b1 #
b0 $
b101 %
1(
b1 *
b0 +
#350000
0!
0(
#355000
1!
b1000 &
b0 '
1(
b1 0
#360000
0!
0(
#365000
1!
b1 #
b1 $
b101 %
1(
b1 +
#370000
0!
0(
#375000
1!
b1 '
1(
b10 0
#380000
0!
0(
#385000
1!
b1 #
b10 $
b101 %
1(
b10 +
#390000
0!
0(
#395000
1!
b10 '
1(
b11 0
#400000
0!
0(
#405000
1!
b1 #
b11 $
b101 %
1(
b11 +
#410000
0!
0(
#415000
1!
b11 '
1(
b100 0
#420000
0!
0(
#425000
1!
b1 #
b100 $
b101 %
1(
b100 +
#430000
0!
0(
#435000
1!
b100 '
1(
b101 0
#440000
0!
0(
#445000
1!
b1 #
b101 $
b101 %
1(
b101 +
#450000
0!
0(
#455000
1!
b101 '
1(
b110 0
#460000
0!
0(
#465000
1!
b1 #
b110 $
b101 %
1(
b110 +
#470000
0!
0(
#475000
1!
b110 '
1(
b111 0
#480000
0!
0(
#485000
1!
b1 #
b111 $
b101 %
1(
b111 +
#490000
0!
0(
#495000
1!
b111 '
1(
b1000 0
#500000
0!
0(
#505000
1!
b1 #
b1000 $
b101 %
1(
b1000 +
#510000
0!
0(
#515000
1!
bx '
1(
b1001 0
#520000
0!
0(
#525000
1!
b1 #
b1001 $
b101 %
1(
b1001 +
#530000
0!
0(
#535000
1!
1(
b1010 0
#540000
0!
0(
#545000
1!
b1 #
b1010 $
b101 %
1(
b1010 +
#550000
0!
0(
#555000
1!
1(
b1011 0
#560000
0!
0(
#565000
1!
b1 #
b1011 $
b101 %
1(
b1011 +
#570000
0!
0(
#575000
1!
1(
b1100 0
#580000
0!
0(
#585000
1!
b1 #
b1100 $
b101 %
1(
b1100 +
#590000
0!
0(
#595000
1!
1(
b1101 0
#600000
0!
0(
#605000
1!
b1 #
b1101 $
b101 %
1(
b1101 +
#610000
0!
0(
#615000
1!
1(
b1110 0
#620000
0!
0(
#625000
1!
b1 #
b1110 $
b101 %
1(
b1110 +
#630000
0!
0(
#635000
1!
1(
b1111 0
#640000
0!
0(
#645000
1!
b1 #
b1111 $
b101 %
1(
b1111 +
#650000
0!
0(
#655000
1!
1(
b10 /
b0 0
#660000
0!
0(
#665000
1!
b10 #
b0 $
b101 %
1(
b10 *
b0 +
#670000
0!
0(
#675000
1!
b10000 &
b0 '
1(
b1 0
#680000
0!
0(
#685000
1!
b10 #
b1 $
b101 %
1(
b1 +
#690000
0!
0(
#695000
1!
b1 '
1(
b10 0
#700000
0!
0(
#705000
1!
b10 #
b10 $
b101 %
1(
b10 +
#710000
0!
0(
#715000
1!
b10 '
1(
b11 0
#720000
0!
0(
#725000
1!
b10 #
b11 $
b101 %
1(
b11 +
#730000
0!
0(
#735000
1!
b11 '
1(
b100 0
#740000
0!
0(
#745000
1!
b10 #
b100 $
b101 %
1(
b100 +
#750000
0!
0(
#755000
1!
b100 '
1(
b101 0
#760000
0!
0(
#765000
1!
b10 #
b101 $
b101 %
1(
b101 +
#770000
0!
0(
#775000
1!
b101 '
1(
b110 0
#780000
0!
0(
#785000
1!
b10 #
b110 $
b101 %
1(
b110 +
#790000
0!
0(
#795000
1!
b110 '
1(
b111 0
#800000
0!
0(
#805000
1!
b10 #
b111 $
b101 %
1(
b111 +
#810000
0!
0(
#815000
1!
b111 '
1(
b1000 0
#820000
0!
0(
#825000
1!
b10 #
b1000 $
b101 %
1(
b1000 +
#830000
0!
0(
#835000
1!
bx '
1(
b1001 0
#840000
0!
0(
#845000
1!
b10 #
b1001 $
b101 %
1(
b1001 +
#850000
0!
0(
#855000
1!
1(
b1010 0
#860000
0!
0(
#865000
1!
b10 #
b1010 $
b101 %
1(
b1010 +
#870000
0!
0(
#875000
1!
1(
b1011 0
#880000
0!
0(
#885000
1!
b10 #
b1011 $
b101 %
1(
b1011 +
#890000
0!
0(
#895000
1!
1(
b1100 0
#900000
0!
0(
#905000
1!
b10 #
b1100 $
b101 %
1(
b1100 +
#910000
0!
0(
#915000
1!
1(
b1101 0
#920000
0!
0(
#925000
1!
b10 #
b1101 $
b101 %
1(
b1101 +
#930000
0!
0(
#935000
1!
1(
b1110 0
#940000
0!
0(
#945000
1!
b10 #
b1110 $
b101 %
1(
b1110 +
#950000
0!
0(
#955000
1!
1(
b1111 0
#960000
0!
0(
#965000
1!
b10 #
b1111 $
b101 %
1(
b1111 +
#970000
0!
0(
#975000
1!
1(
b11 /
b0 0
#980000
0!
0(
#985000
1!
b11 #
b0 $
b101 %
1(
b11 *
b0 +
#990000
0!
0(
#995000
1!
b11000 &
b0 '
1(
b1 0
