intra_prediction.srcs/sources_1/new/reference_sample_arrays.sv
`timescale 1ns / 1ps
//////////////////////////////////////////////////////////////////////////////////
// Company: 
// Engineer: 
// 
// Create Date: 08/20/2025 02:21:47 AM
// Design Name: 
// Module Name: reference_sample_arrays
// Project Name: 
// Target Devices: 
// Tool Versions: 
// Description: 
// 
// Dependencies: 
// 
// Revision:
// Revision 0.01 - File Created
// Additional Comments:
// 
//////////////////////////////////////////////////////////////////////////////////


module reference_sample_arrays(
    input clk,
    input rst,
    input logic signed [3:0]x,
    input logic signed [3:0]y,
    input logic signed [7:0]B,
    output logic [7:0] ref_out1,   //For X
    output logic [7:0] ref_out2   //For Y
     );
    
    logic [7:0] p [0:7][0:7]; //2 D Pixel Array
    
    logic [7:0] ref_x[0:7];  //Reference Array X
    logic [7:0] ref_y[0:7]; //Reference Array y
        
        
    // The values of p are determined by other inputs or logic
        always_comb begin
            for (int i = 0; i < 8; i++) begin
                for (int j = 0; j < 8; j++) begin
                    // Example: Initialize based on inputs x and y
                    p[i][j] = (i * 8) + j; 
                end
            end
        end    
    
    //Reference X Equations
    always_comb begin
    if(x>0)
    ref_x[x]= p[x][0]; //Equation 4.8  x > 0 Vertical Mode  
    else 
    ref_x[x]=(p[0][-1 + (x*B) + 128 >>8]) ; // Equation 4.10 
    end
    
    //Reference Y Equations
        always_comb begin
        if(y>0)
        ref_y[y]= p[0][y]; //Equation 4.9  x > 0 Horizontal Mode p[-1][-1+y]  
        else 
        ref_y[y]= p[-1 + (y*B) + 128 >> 8][0] ; // Equation 4.11 
        end
        
    always_ff@(posedge clk)
    if(rst)
    ref_out1<=0;
    else
    ref_out1<=ref_x[x];
    
    always_ff@(posedge clk)
     if(rst)
     ref_out2<=0;
     else
    ref_out2<=ref_y[y];
        
    
endmodule

intra_prediction.srcs/sim_1/new/tb_reference_array.sv
`timescale 1ns / 1ps
//////////////////////////////////////////////////////////////////////////////////
// Company: 
// Engineer: 
// 
// Create Date: 08/20/2025 02:42:13 AM
// Design Name: 
// Module Name: tb_reference_array
// Project Name: 
// Target Devices: 
// Tool Versions: 
// Description: 
// 
// Dependencies: 
// 
// Revision:
// Revision 0.01 - File Created
// Additional Comments:
// 
//////////////////////////////////////////////////////////////////////////////////

`timescale 1ns/1ps

module tb_reference_sample_arrays;

  // Testbench signals
  logic clk;
  logic rst;
  logic [3:0] x, y;
  logic [7:0] B;
  logic [7:0] ref_out1, ref_out2;

  // Instantiate DUT
  reference_sample_arrays dut (
    .clk(clk),
    .rst(rst),
    .x(x),
    .y(y),
    .B(B),
    .ref_out1(ref_out1),
    .ref_out2(ref_out2)
  );

  // Clock generation
  initial clk = 0;
  always #5 clk = ~clk;   // 10ns period

  // Stimulus
  initial begin
    // Initialize
    rst = 1;
    B = 8'd5;   // Example value for B
    x = 0;
    y = 0;

    // Apply reset
    #20;
    rst = 0;


        for (int xi = 0; xi <= 15; xi++) begin
      for (int yi = 0; yi <= 15; yi++) begin
        @(posedge clk);  // <<< Apply at clock edge
        x <= xi;
        y <= yi;
        B <= 8'd5; // Example constant
        @(posedge clk); // Wait for DUT to update outputs
    
        $display("Time=%0t | x=%0d | y=%0d | ref_out1=%0d | ref_out2=%0d",
                 $time, x, y, ref_out1, ref_out2);
      end
    end


    // End simulation
    $display("Simulation completed at %0t", $time);
    $finish;
  end

  // VCD dump for GTKWave
  initial begin
    $dumpfile("reference_sample_arrays_tb.vcd");
    $dumpvars(0, tb_reference_sample_arrays);
  end

endmodule

intra_prediction.sim/sim_1/behav/xsim/reference_sample_arrays_tb.vcd
$date
   Wed Aug 20 04:40:07 2025
$end
$version
  2018.2
$end
$timescale
  1ps
$end
$scope module tb_reference_sample_arrays $end
$var reg 1 ! clk $end
$var reg 1 " rst $end
$var reg 4 # x [3:0] $end
$var reg 4 $ y [3:0] $end
$var reg 8 % B [7:0] $end
$var reg 8 & ref_out1 [7:0] $end
$var reg 8 ' ref_out2 [7:0] $end
$scope module dut $end
$var wire 1 ( clk $end
$var wire 1 ) rst $end
$var wire 4 * x [3:0] $end
$var wire 4 + y [3:0] $end
$var wire 8 , B [7:0] $end
$var reg 8 & ref_out1 [7:0] $end
$var reg 8 ' ref_out2 [7:0] $end
$scope begin Block41_1 $end
$var reg 32 - i $end
$scope begin Block42_2 $end
$var reg 32 . j $end
$upscope $end
$upscope $end
$upscope $end
$scope begin Block61_10 $end
$var reg 32 / xi $end
$scope begin Block62_11 $end
$var reg 32 0 yi $end
$upscope $end
$upscope $end
$upscope $end
$enddefinitions $end
#0
$dumpvars
0!
1"
b0 #
b0 $
b101 %
bx &
bx '
0(
1)
b0 *
b0 +
b101 ,
b1000 -
b1000 .
b0 /
b0 0
$end
#5000
1!
b0 &
b0 '
1(
#10000
0!
0(
#15000
1!
1(
#20000
0!
0"
0(
0)
#25000
1!
b0 #
b0 $
b101 %
1(
#30000
0!
0(
#35000
1!
1(
b1 0
#40000
0!
0(
#45000
1!
b0 #
b1 $
b101 %
1(
b1 +
#50000
0!
0(
#55000
1!
b1 '
1(
b10 0
#60000
0!
0(
#65000
1!
b0 #
b10 $
b101 %
1(
b10 +
#70000
0!
0(
#75000
1!
b10 '
1(
b11 0
#80000
0!
0(
#85000
1!
b0 #
b11 $
b101 %
1(
b11 +
#90000
0!
0(
#95000
1!
b11 '
1(
b100 0
#100000
0!
0(
#105000
1!
b0 #
b100 $
b101 %
1(
b100 +
#110000
0!
0(
#115000
1!
b100 '
1(
b101 0
#120000
0!
0(
#125000
1!
b0 #
b101 $
b101 %
1(
b101 +
#130000
0!
0(
#135000
1!
b101 '
1(
b110 0
#140000
0!
0(
#145000
1!
b0 #
b110 $
b101 %
1(
b110 +
#150000
0!
0(
#155000
1!
b110 '
1(
b111 0
#160000
0!
0(
#165000
1!
b0 #
b111 $
b101 %
1(
b111 +
#170000
0!
0(
#175000
1!
b111 '
1(
b1000 0
#180000
0!
0(
#185000
1!
b0 #
b1000 $
b101 %
1(
b1000 +
#190000
0!
0(
#195000
1!
bx '
1(
b1001 0
#200000
0!
0(
#205000
1!
b0 #
b1001 $
b101 %
1(
b1001 +
#210000
0!
0(
#215000
1!
1(
b1010 0
#220000
0!
0(
#225000
1!
b0 #
b1010 $
b101 %
1(
b1010 +
#230000
0!
0(
#235000
1!
1(
b1011 0
#240000
0!
0(
#245000
1!
b0 #
b1011 $
b101 %
1(
b1011 +
#250000
0!
0(
#255000
1!
1(
b1100 0
#260000
0!
0(
#265000
1!
b0 #
b1100 $
b101 %
1(
b1100 +
#270000
0!
0(
#275000
1!
1(
b1101 0
#280000
0!
0(
#285000
1!
b0 #
b1101 $
b101 %
1(
b1101 +
#290000
0!
0(
#295000
1!
1(
b1110 0
#300000
0!
0(
#305000
1!
b0 #
b1110 $
b101 %
1(
b1110 +
#310000
0!
0(
#315000
1!
1(
b1111 0
#320000
0!
0(
#325000
1!
b0 #
b1111 $
b101 %
1(
b1111 +
#330000
0!
0(
#335000
1!
1(
b1 /
b0 0
#340000
0!
0(
#345000
1!
b1 #
b0 $
b101 %
1(
b1 *
b0 +
#350000
0!
0(
#355000
1!
b1000 &
b0 '
1(
b1 0
#360000
0!
0(
#365000
1!
b1 #
b1 $
b101 %
1(
b1 +
#370000
0!
0(
#375000
1!
b1 '
1(
b10 0
#380000
0!
0(
#385000
1!
b1 #
b10 $
b101 %
1(
b10 +
#390000
0!
0(
#395000
1!
b10 '
1(
b11 0
#400000
0!
0(
#405000
1!
b1 #
b11 $
b101 %
1(
b11 +
#410000
0!
0(
#415000
1!
b11 '
1(
b100 0
#420000
0!
0(
#425000
1!
b1 #
b100 $
b101 %
1(
b100 +
#430000
0!
0(
#435000
1!
b100 '
1(
b101 0
#440000
0!
0(
#445000
1!
b1 #
b101 $
b101 %
1(
b101 +
#450000
0!
0(
#455000
1!
b101 '
1(
b110 0
#460000
0!
0(
#465000
1!
b1 #
b110 $
b101 %
1(
b110 +
#470000
0!
0(
#475000
1!
b110 '
1(
b111 0
#480000
0!
0(
#485000
1!
b1 #
b111 $
b101 %
1(
b111 +
#490000
0!
0(
#495000
1!
b111 '
1(
b1000 0
#500000
0!
0(
#505000
1!
b1 #
b1000 $
b101 %
1(
b1000 +
#510000
0!
0(
#515000
1!
bx '
1(
b1001 0
#520000
0!
0(
#525000
1!
b1 #
b1001 $
b101 %
1(
b1001 +
#530000
0!
0(
#535000
1!
1(
b1010 0
#540000
0!
0(
#545000
1!
b1 #
b1010 $
b101 %
1(
b1010 +
#550000
0!
0(
#555000
1!
1(
b1011 0
#560000
0!
0(
#565000
1!
b1 #
b1011 $
b101 %
1(
b1011 +
#570000
0!
0(
#575000
1!
1(
b1100 0
#580000
0!
0(
#585000
1!
b1 #
b1100 $
b101 %
1(
b1100 +
#590000
0!
0(
#595000
1!
1(
b1101 0
#600000
0!
0(
#605000
1!
b1 #
b1101 $
b101 %
1(
b1101 +
#610000
0!
0(
#615000
1!
1(
b1110 0
#620000
0!
0(
#625000
1!
b1 #
b1110 $
b101 %
1(
b1110 +
#630000
0!
0(
#635000
1!
1(
b1111 0
#640000
0!
0(
#645000
1!
b1 #
b1111 $
b101 %
1(
b1111 +
#650000
0!
0(
#655000
1!
1(
b10 /
b0 0
#660000
0!
0(
#665000
1!
b10 #
b0 $
b101 %
1(
b10 *
b0 +
#670000
0!
0(
#675000
1!
b10000 &
b0 '
1(
b1 0
#680000
0!
0(
#685000
1!
b10 #
b1 $
b101 %
1(
b1 +
#690000
0!
0(
#695000
1!
b1 '
1(
b10 0
#700000
0!
0(
#705000
1!
b10 #
b10 $
b101 %
1(
b10 +
#710000
0!
0(
#715000
1!
b10 '
1(
b11 0
#720000
0!
0(
#725000
1!
b10 #
b11 $
b101 %
1(
b11 +
#730000
0!
0(
#735000
1!
b11 '
1(
b100 0
#740000
0!
0(
#745000
1!
b10 #
b100 $
b101 %
1(
b100 +
#750000
0!
0(
#755000
1!
b100 '
1(
b101 0
#760000
0!
0(
#765000
1!
b10 #
b101 $
b101 %
1(
b101 +
#770000
0!
0(
#775000
1!
b101 '
1(
b110 0
#780000
0!
0(
#785000
1!
b10 #
b110 $
b101 %
1(
b110 +
#790000
0!
0(
#795000
1!
b110 '
1(
b111 0
#800000
0!
0(
#805000
1!
b10 #
b111 $
b101 %
1(
b111 +
#810000
0!
0(
#815000
1!
b111 '
1(
b1000 0
#820000
0!
0(
#825000
1!
b10 #
b1000 $
b101 %
1(
b1000 +
#830000
0!
0(
#835000
1!
bx '
1(
b1001 0
#840000
0!
0(
#845000
1!
b10 #
b1001 $
b101 %
1(
b1001 +
#850000
0!
0(
#855000
1!
1(
b1010 0
#860000
0!
0(
#865000
1!
b10 #
b1010 $
b101 %
1(
b1010 +
#870000
0!
0(
#875000
1!
1(
b1011 0
#880000
0!
0(
#885000
1!
b10 #
b1011 $
b101 %
1(
b1011 +
#890000
0!
0(
#895000
1!
1(
b1100 0
#900000
0!
0(
#905000
1!
b10 #
b1100 $
b101 %
1(
b1100 +
#910000
0!
0(
#915000
1!
1(
b1101 0
#920000
0!
0(
#925000
1!
b10 #
b1101 $
b101 %
1(
b1101 +
#930000
0!
0(
#935000
1!
1(
b1110 0
#940000
0!
0(
#945000
1!
b10 #
b1110 $
b101 %
1(
b1110 +
#950000
0!
0(
#955000
1!
1(
b1111 0
#960000
0!
0(
#965000
1!
b10 #
b1111 $
b101 %
1(
b1111 +
#970000
0!
0(
#975000
1!
1(
b11 /
b0 0
#980000
0!
0(
#985000
1!
b11 #
b0 $
b101 %
1(
b11 *
b0 +
#990000
0!
0(
#995000
1!
b11000 &
b0 '
1(
b1 0
#1000000
0!
0(
#1005000
1!
b11 #
b1 $
b101 %
1(
b1 +
#1010000
0!
0(
#1015000
1!
b1 '
1(
b10 0
#1020000
0!
0(
#1025000
1!
b11 #
b10 $
b101 %
1(
b10 +
#1030000
0!
0(
#1035000
1!
b10 '
1(
b11 0
#1040000
0!
0(
#1045000
1!
b11 #
b11 $
b101 %
1(
b11 +
#1050000
0!
0(
#1055000
1!
b11 '
1(
b100 0
#1060000
0!
0(
#1065000
1!
b11 #
b100 $
b101 %
1(
b100 +
#1070000
0!
0(
#1075000
1!
b100 '
1(
b101 0
#1080000
0!
0(
#1085000
1!
b11 #
b101 $
b101 %
1(
b101 +
#1090000
0!
0(
#1095000
1!
b101 '
1(
b110 0
#1100000
0!
0(
#1105000
1!
b11 #
b110 $
b101 %
1(
b110 +
#1110000
0!
0(
#1115000
1!
b110 '
1(
b111 0
#1120000
0!
0(
#1125000
1!
b11 #
b111 $
b101 %
1(
b111 +
#1130000
0!
0(
#1135000
1!
b111 '
1(
b1000 0
#1140000
0!
0(
#1145000
1!
b11 #
b1000 $
b101 %
1(
b1000 +
#1150000
0!
0(
#1155000
1!
bx '
1(
b1001 0
#1160000
0!
0(
#1165000
1!
b11 #
b1001 $
b101 %
1(
b1001 +
#1170000
0!
0(
#1175000
1!
1(
b1010 0
#1180000
0!
0(
#1185000
1!
b11 #
b1010 $
b101 %
1(
b1010 +
#1190000
0!
0(
#1195000
1!
1(
b1011 0
#1200000
0!
0(
#1205000
1!
b11 #
b1011 $
b101 %
1(
b1011 +
#1210000
0!
0(
#1215000
1!
1(
b1100 0
#1220000
0!
0(
#1225000
1!
b11 #
b1100 $
b101 %
1(
b1100 +
#1230000
0!
0(
#1235000
1!
1(
b1101 0
#1240000
0!
0(
#1245000
1!
b11 #
b1101 $
b101 %
1(
b1101 +
#1250000
0!
0(
#1255000
1!
1(
b1110 0
#1260000
0!
0(
#1265000
1!
b11 #
b1110 $
b101 %
1(
b1110 +
#1270000
0!
0(
#1275000
1!
1(
b1111 0
#1280000
0!
0(
#1285000
1!
b11 #
b1111 $
b101 %
1(
b1111 +
#1290000
0!
0(
#1295000
1!
1(
b100 /
b0 0
#1300000
0!
0(
#1305000
1!
b100 #
b0 $
b101 %
1(
b100 *
b0 +
#1310000
0!
0(
#1315000
1!
b100000 &
b0 '
1(
b1 0
#1320000
0!
0(
#1325000
1!
b100 #
b1 $
b101 %
1(
b1 +
#1330000
0!
0(
#1335000
1!
b1 '
1(
b10 0
#1340000
0!
0(
#1345000
1!
b100 #
b10 $
b101 %
1(
b10 +
#1350000
0!
0(
#1355000
1!
b10 '
1(
b11 0
#1360000
0!
0(
#1365000
1!
b100 #
b11 $
b101 %
1(
b11 +
#1370000
0!
0(
#1375000
1!
b11 '
1(
b100 0
#1380000
0!
0(
#1385000
1!
b100 #
b100 $
b101 %
1(
b100 +
#1390000
0!
0(
#1395000
1!
b100 '
1(
b101 0
#1400000
0!
0(
#1405000
1!
b100 #
b101 $
b101 %
1(
b101 +
#1410000
0!
0(
#1415000
1!
b101 '
1(
b110 0
#1420000
0!
0(
#1425000
1!
b100 #
b110 $
b101 %
1(
b110 +
#1430000
0!
0(
#1435000
1!
b110 '
1(
b111 0
#1440000
0!
0(
#1445000
1!
b100 #
b111 $
b101 %
1(
b111 +
#1450000
0!
0(
#1455000
1!
b111 '
1(
b1000 0
#1460000
0!
0(
#1465000
1!
b100 #
b1000 $
b101 %
1(
b1000 +
#1470000
0!
0(
#1475000
1!
bx '
1(
b1001 0
#1480000
0!
0(
#1485000
1!
b100 #
b1001 $
b101 %
1(
b1001 +
#1490000
0!
0(
#1495000
1!
1(
b1010 0
#1500000
0!
0(
#1505000
1!
b100 #
b1010 $
b101 %
1(
b1010 +
#1510000
0!
0(
#1515000
1!
1(
b1011 0
#1520000
0!
0(
#1525000
1!
b100 #
b1011 $
b101 %
1(
b1011 +
#1530000
0!
0(
#1535000
1!
1(
b1100 0
#1540000
0!
0(
#1545000
1!
b100 #
b1100 $
b101 %
1(
b1100 +
#1550000
0!
0(
#1555000
1!
1(
b1101 0
#1560000
0!
0(
#1565000
1!
b100 #
b1101 $
b101 %
1(
b1101 +
#1570000
0!
0(
#1575000
1!
1(
b1110 0
#1580000
0!
0(
#1585000
1!
b100 #
b1110 $
b101 %
1(
b1110 +
#1590000
0!
0(
#1595000
1!
1(
b1111 0
#1600000
0!
0(
#1605000
1!
b100 #
b1111 $
b101 %
1(
b1111 +
#1610000
0!
0(
#1615000
1!
1(
b101 /
b0 0
#1620000
0!
0(
#1625000
1!
b101 #
b0 $
b101 %
1(
b101 *
b0 +
#1630000
0!
0(
#1635000
1!
b101000 &
b0 '
1(
b1 0
#1640000
0!
0(
#1645000
1!
b101 #
b1 $
b101 %
1(
b1 +
#1650000
0!
0(
#1655000
1!
b1 '
1(
b10 0
#1660000
0!
0(
#1665000
1!
b101 #
b10 $
b101 %
1(
b10 +
#1670000
0!
0(
#1675000
1!
b10 '
1(
b11 0
#1680000
0!
0(
#1685000
1!
b101 #
b11 $
b101 %
1(
b11 +
#1690000
0!
0(
#1695000
1!
b11 '
1(
b100 0
#1700000
0!
0(
#1705000
1!
b101 #
b100 $
b101 %
1(
b100 +
#1710000
0!
0(
#1715000
1!
b100 '
1(
b101 0
#1720000
0!
0(
#1725000
1!
b101 #
b101 $
b101 %
1(
b101 +
#1730000
0!
0(
#1735000
1!
b101 '
1(
b110 0
#1740000
0!
0(
#1745000
1!
b101 #
b110 $
b101 %
1(
b110 +
#1750000
0!
0(
#1755000
1!
b110 '
1(
b111 0
#1760000
0!
0(
#1765000
1!
b101 #
b111 $
b101 %
1(
b111 +
#1770000
0!
0(
#1775000
1!
b111 '
1(
b1000 0
#1780000
0!
0(
#1785000
1!
b101 #
b1000 $
b101 %
1(
b1000 +
#1790000
0!
0(
#1795000
1!
bx '
1(
b1001 0
#1800000
0!
0(
#1805000
1!
b101 #
b1001 $
b101 %
1(
b1001 +
#1810000
0!
0(
#1815000
1!
1(
b1010 0
#1820000
0!
0(
#1825000
1!
b101 #
b1010 $
b101 %
1(
b1010 +
#1830000
0!
0(
#1835000
1!
1(
b1011 0
#1840000
0!
0(
#1845000
1!
b101 #
b1011 $
b101 %
1(
b1011 +
#1850000
0!
0(
#1855000
1!
1(
b1100 0
#1860000
0!
0(
#1865000
1!
b101 #
b1100 $
b101 %
1(
b1100 +
#1870000
0!
0(
#1875000
1!
1(
b1101 0
#1880000
0!
0(
#1885000
1!
b101 #
b1101 $
b101 %
1(
b1101 +
#1890000
0!
0(
#1895000
1!
1(
b1110 0
#1900000
0!
0(
#1905000
1!
b101 #
b1110 $
b101 %
1(
b1110 +
#1910000
0!
0(
#1915000
1!
1(
b1111 0
#1920000
0!
0(
#1925000
1!
b101 #
b1111 $
b101 %
1(
b1111 +
#1930000
0!
0(
#1935000
1!
1(
b110 /
b0 0
#1940000
0!
0(
#1945000
1!
b110 #
b0 $
b101 %
1(
b110 *
b0 +
#1950000
0!
0(
#1955000
1!
b110000 &
b0 '
1(
b1 0
#1960000
0!
0(
#1965000
1!
b110 #
b1 $
b101 %
1(
b1 +
#1970000
0!
0(
#1975000
1!
b1 '
1(
b10 0
#1980000
0!
0(
#1985000
1!
b110 #
b10 $
b101 %
1(
b10 +
#1990000
0!
0(
#1995000
1!
b10 '
1(
b11 0
#2000000
0!
0(
#2005000
1!
b110 #
b11 $
b101 %
1(
b11 +
#2010000
0!
0(
#2015000
1!
b11 '
1(
b100 0
#2020000
0!
0(
#2025000
1!
b110 #
b100 $
b101 %
1(
b100 +
#2030000
0!
0(
#2035000
1!
b100 '
1(
b101 0
#2040000
0!
0(
#2045000
1!
b110 #
b101 $
b101 %
1(
b101 +
#2050000
0!
0(
#2055000
1!
b101 '
1(
b110 0
#2060000
0!
0(
#2065000
1!
b110 #
b110 $
b101 %
1(
b110 +
#2070000
0!
0(
#2075000
1!
b110 '
1(
b111 0
#2080000
0!
0(
#2085000
1!
b110 #
b111 $
b101 %
1(
b111 +
#2090000
0!
0(
#2095000
1!
b111 '
1(
b1000 0
#2100000
0!
0(
#2105000
1!
b110 #
b1000 $
b101 %
1(
b1000 +
#2110000
0!
0(
#2115000
1!
bx '
1(
b1001 0
#2120000
0!
0(
#2125000
1!
b110 #
b1001 $
b101 %
1(
b1001 +
#2130000
0!
0(
#2135000
1!
1(
b1010 0
#2140000
0!
0(
#2145000
1!
b110 #
b1010 $
b101 %
1(
b1010 +
#2150000
0!
0(
#2155000
1!
1(
b1011 0
#2160000
0!
0(
#2165000
1!
b110 #
b1011 $
b101 %
1(
b1011 +
#2170000
0!
0(
#2175000
1!
1(
b1100 0
#2180000
0!
0(
#2185000
1!
b110 #
b1100 $
b101 %
1(
b1100 +
#2190000
0!
0(
#2195000
1!
1(
b1101 0
#2200000
0!
0(
#2205000
1!
b110 #
b1101 $
b101 %
1(
b1101 +
#2210000
0!
0(
#2215000
1!
1(
b1110 0
#2220000
0!
0(
#2225000
1!
b110 #
b1110 $
b101 %
1(
b1110 +
#2230000
0!
0(
#2235000
1!
1(
b1111 0
#2240000
0!
0(
#2245000
1!
b110 #
b1111 $
b101 %
1(
b1111 +
#2250000
0!
0(
#2255000
1!
1(
b111 /
b0 0
#2260000
0!
0(
#2265000
1!
b111 #
b0 $
b101 %
1(
b111 *
b0 +
#2270000
0!
0(
#2275000
1!
b111000 &
b0 '
1(
b1 0
#2280000
0!
0(
#2285000
1!
b111 #
b1 $
b101 %
1(
b1 +
#2290000
0!
0(
#2295000
1!
b1 '
1(
b10 0
#2300000
0!
0(
#2305000
1!
b111 #
b10 $
b101 %
1(
b10 +
#2310000
0!
0(
#2315000
1!
b10 '
1(
b11 0
#2320000
0!
0(
#2325000
1!
b111 #
b11 $
b101 %
1(
b11 +
#2330000
0!
0(
#2335000
1!
b11 '
1(
b100 0
#2340000
0!
0(
#2345000
1!
b111 #
b100 $
b101 %
1(
b100 +
#2350000
0!
0(
#2355000
1!
b100 '
1(
b101 0
#2360000
0!
0(
#2365000
1!
b111 #
b101 $
b101 %
1(
b101 +
#2370000
0!
0(
#2375000
1!
b101 '
1(
b110 0
#2380000
0!
0(
#2385000
1!
b111 #
b110 $
b101 %
1(
b110 +
#2390000
0!
0(
#2395000
1!
b110 '
1(
b111 0
#2400000
0!
0(
#2405000
1!
b111 #
b111 $
b101 %
1(
b111 +
#2410000
0!
0(
#2415000
1!
b111 '
1(
b1000 0
#2420000
0!
0(
#2425000
1!
b111 #
b1000 $
b101 %
1(
b1000 +
#2430000
0!
0(
#2435000
1!
bx '
1(
b1001 0
#2440000
0!
0(
#2445000
1!
b111 #
b1001 $
b101 %
1(
b1001 +
#2450000
0!
0(
#2455000
1!
1(
b1010 0
#2460000
0!
0(
#2465000
1!
b111 #
b1010 $
b101 %
1(
b1010 +
#2470000
0!
0(
#2475000
1!
1(
b1011 0
#2480000
0!
0(
#2485000
1!
b111 #
b1011 $
b101 %
1(
b1011 +
#2490000
0!
0(
#2495000
1!
1(
b1100 0
#2500000
0!
0(
#2505000
1!
b111 #
b1100 $
b101 %
1(
b1100 +
#2510000
0!
0(
#2515000
1!
1(
b1101 0
#2520000
0!
0(
#2525000
1!
b111 #
b1101 $
b101 %
1(
b1101 +
#2530000
0!
0(
#2535000
1!
1(
b1110 0
#2540000
0!
0(
#2545000
1!
b111 #
b1110 $
b101 %
1(
b1110 +
#2550000
0!
0(
#2555000
1!
1(
b1111 0
#2560000
0!
0(
#2565000
1!
b111 #
b1111 $
b101 %
1(
b1111 +
#2570000
0!
0(
#2575000
1!
1(
b1000 /
b0 0
#2580000
0!
0(
#2585000
1!
b1000 #
b0 $
b101 %
1(
b1000 *
b0 +
#2590000
0!
0(
#2595000
1!
bx &
b0 '
1(
b1 0
#2600000
0!
0(
#2605000
1!
b1000 #
b1 $
b101 %
1(
b1 +
#2610000
0!
0(
#2615000
1!
b1 '
1(
b10 0
#2620000
0!
0(
#2625000
1!
b1000 #
b10 $
b101 %
1(
b10 +
#2630000
0!
0(
#2635000
1!
b10 '
1(
b11 0
#2640000
0!
0(
#2645000
1!
b1000 #
b11 $
b101 %
1(
b11 +
#2650000
0!
0(
#2655000
1!
b11 '
1(
b100 0
#2660000
0!
0(
#2665000
1!
b1000 #
b100 $
b101 %
1(
b100 +
#2670000
0!
0(
#2675000
1!
b100 '
1(
b101 0
#2680000
0!
0(
#2685000
1!
b1000 #
b101 $
b101 %
1(
b101 +
#2690000
0!
0(
#2695000
1!
b101 '
1(
b110 0
#2700000
0!
0(
#2705000
1!
b1000 #
b110 $
b101 %
1(
b110 +
#2710000
0!
0(
#2715000
1!
b110 '
1(
b111 0
#2720000
0!
0(
#2725000
1!
b1000 #
b111 $
b101 %
1(
b111 +
#2730000
0!
0(
#2735000
1!
b111 '
1(
b1000 0
#2740000
0!
0(
#2745000
1!
b1000 #
b1000 $
b101 %
1(
b1000 +
#2750000
0!
0(
#2755000
1!
bx '
1(
b1001 0
#2760000
0!
0(
#2765000
1!
b1000 #
b1001 $
b101 %
1(
b1001 +
#2770000
0!
0(
#2775000
1!
1(
b1010 0
#2780000
0!
0(
#2785000
1!
b1000 #
b1010 $
b101 %
1(
b1010 +
#2790000
0!
0(
#2795000
1!
1(
b1011 0
#2800000
0!
0(
#2805000
1!
b1000 #
b1011 $
b101 %
1(
b1011 +
#2810000
0!
0(
#2815000
1!
1(
b1100 0
#2820000
0!
0(
#2825000
1!
b1000 #
b1100 $
b101 %
1(
b1100 +
#2830000
0!
0(
#2835000
1!
1(
b1101 0
#2840000
0!
0(
#2845000
1!
b1000 #
b1101 $
b101 %
1(
b1101 +
#2850000
0!
0(
#2855000
1!
1(
b1110 0
#2860000
0!
0(
#2865000
1!
b1000 #
b1110 $
b101 %
1(
b1110 +
#2870000
0!
0(
#2875000
1!
1(
b1111 0
#2880000
0!
0(
#2885000
1!
b1000 #
b1111 $
b101 %
1(
b1111 +
#2890000
0!
0(
#2895000
1!
1(
b1001 /
b0 0
#2900000
0!
0(
#2905000
1!
b1001 #
b0 $
b101 %
1(
b1001 *
b0 +
#2910000
0!
0(
#2915000
1!
b0 '
1(
b1 0
#2920000
0!
0(
#2925000
1!
b1001 #
b1 $
b101 %
1(
b1 +
#2930000
0!
0(
#2935000
1!
b1 '
1(
b10 0
#2940000
0!
0(
#2945000
1!
b1001 #
b10 $
b101 %
1(
b10 +
#2950000
0!
0(
#2955000
1!
b10 '
1(
b11 0
#2960000
0!
0(
#2965000
1!
b1001 #
b11 $
b101 %
1(
b11 +
#2970000
0!
0(
#2975000
1!
b11 '
1(
b100 0
#2980000
0!
0(
#2985000
1!
b1001 #
b100 $
b101 %
1(
b100 +
#2990000
0!
0(
#2995000
1!
b100 '
1(
b101 0
#3000000
0!
0(
#3005000
1!
b1001 #
b101 $
b101 %
1(
b101 +
#3010000
0!
0(
#3015000
1!
b101 '
1(
b110 0
#3020000
0!
0(
#3025000
1!
b1001 #
b110 $
b101 %
1(
b110 +
#3030000
0!
0(
#3035000
1!
b110 '
1(
b111 0
#3040000
0!
0(
#3045000
1!
b1001 #
b111 $
b101 %
1(
b111 +
#3050000
0!
0(
#3055000
1!
b111 '
1(
b1000 0
#3060000
0!
0(
#3065000
1!
b1001 #
b1000 $
b101 %
1(
b1000 +
#3070000
0!
0(
#3075000
1!
bx '
1(
b1001 0
#3080000
0!
0(
#3085000
1!
b1001 #
b1001 $
b101 %
1(
b1001 +
#3090000
0!
0(
#3095000
1!
1(
b1010 0
#3100000
0!
0(
#3105000
1!
b1001 #
b1010 $
b101 %
1(
b1010 +
#3110000
0!
0(
#3115000
1!
1(
b1011 0
#3120000
0!
0(
#3125000
1!
b1001 #
b1011 $
b101 %
1(
b1011 +
#3130000
0!
0(
#3135000
1!
1(
b1100 0
#3140000
0!
0(
#3145000
1!
b1001 #
b1100 $
b101 %
1(
b1100 +
#3150000
0!
0(
#3155000
1!
1(
b1101 0
#3160000
0!
0(
#3165000
1!
b1001 #
b1101 $
b101 %
1(
b1101 +
#3170000
0!
0(
#3175000
1!
1(
b1110 0
#3180000
0!
0(
#3185000
1!
b1001 #
b1110 $
b101 %
1(
b1110 +
#3190000
0!
0(
#3195000
1!
1(
b1111 0
#3200000
0!
0(
#3205000
1!
b1001 #
b1111 $
b101 %
1(
b1111 +
#3210000
0!
0(
#3215000
1!
1(
b1010 /
b0 0
#3220000
0!
0(
#3225000
1!
b1010 #
b0 $
b101 %
1(
b1010 *
b0 +
#3230000
0!
0(
#3235000
1!
b0 '
1(
b1 0
#3240000
0!
0(
#3245000
1!
b1010 #
b1 $
b101 %
1(
b1 +
#3250000
0!
0(
#3255000
1!
b1 '
1(
b10 0
#3260000
0!
0(
#3265000
1!
b1010 #
b10 $
b101 %
1(
b10 +
#3270000
0!
0(
#3275000
1!
b10 '
1(
b11 0
#3280000
0!
0(
#3285000
1!
b1010 #
b11 $
b101 %
1(
b11 +
#3290000
0!
0(
#3295000
1!
b11 '
1(
b100 0
#3300000
0!
0(
#3305000
1!
b1010 #
b100 $
b101 %
1(
b100 +
#3310000
0!
0(
#3315000
1!
b100 '
1(
b101 0
#3320000
0!
0(
#3325000
1!
b1010 #
b101 $
b101 %
1(
b101 +
#3330000
0!
0(
#3335000
1!
b101 '
1(
b110 0
#3340000
0!
0(
#3345000
1!
b1010 #
b110 $
b101 %
1(
b110 +
#3350000
0!
0(
#3355000
1!
b110 '
1(
b111 0
#3360000
0!
0(
#3365000
1!
b1010 #
b111 $
b101 %
1(
b111 +
#3370000
0!
0(
#3375000
1!
b111 '
1(
b1000 0
#3380000
0!
0(
#3385000
1!
b1010 #
b1000 $
b101 %
1(
b1000 +
#3390000
0!
0(
#3395000
1!
bx '
1(
b1001 0
#3400000
0!
0(
#3405000
1!
b1010 #
b1001 $
b101 %
1(
b1001 +
#3410000
0!
0(
#3415000
1!
1(
b1010 0
#3420000
0!
0(
#3425000
1!
b1010 #
b1010 $
b101 %
1(
b1010 +
#3430000
0!
0(
#3435000
1!
1(
b1011 0
#3440000
0!
0(
#3445000
1!
b1010 #
b1011 $
b101 %
1(
b1011 +
#3450000
0!
0(
